toff/__init__.py
toff/_version.py
toff/cli.py
toff/utils.py
toff-0.2.1.dist-info/licenses/LICENSE
toff-0.2.1.dist-info/METADATA
toff-0.2.1.dist-info/WHEEL
toff-0.2.1.dist-info/entry_points.txt
toff-0.2.1.dist-info/top_level.txt
toff-0.2.1.dist-info/RECORD
