Metadata-Version: 2.4
Name: toff
Version: 0.2.1
Summary: toff is a python package to get topologies from open force fields.
Author-email: Alejandro Martínez León <ale94mleon@gmail.com>
Project-URL: Hompage, https://github.com/ale94mleon/toff
Project-URL: Discussions, https://github.com/ale94mleon/toff/discussions
Project-URL: Documentation, https://toff.readthedocs.io/en/latest/
Project-URL: Issues, https://github.com/ale94mleon/toff/issues
Keywords: science,chemistry,biology,drug-design,molecular-dynamic
Classifier: Development Status :: 2 - Pre-Alpha
Classifier: Operating System :: POSIX :: Linux
Classifier: Operating System :: MacOS
Classifier: Intended Audience :: Science/Research
Classifier: License :: OSI Approved :: Apache Software License
Classifier: Programming Language :: Python :: 3
Classifier: Programming Language :: Python :: 3.9
Classifier: Programming Language :: Python :: 3.10
Classifier: Programming Language :: Python :: 3.11
Classifier: Programming Language :: Python :: 3.12
Classifier: Topic :: Scientific/Engineering :: Bio-Informatics
Classifier: Topic :: Scientific/Engineering :: Chemistry
Classifier: Topic :: Scientific/Engineering :: Physics
Requires-Python: >3.8
License-File: LICENSE
Requires-Dist: pyyaml
Requires-Dist: rdkit
Provides-Extra: dev
Requires-Dist: pytest; extra == "dev"
Dynamic: license-file
